TextPreprocessing/__init__.py
TextPreprocessing/preprocess.py
TextPreprocessing/utility.py
TextPreprocessing-3.4.0.dist-info/METADATA
TextPreprocessing-3.4.0.dist-info/WHEEL
TextPreprocessing-3.4.0.dist-info/top_level.txt
TextPreprocessing-3.4.0.dist-info/RECORD
