Metadata-Version: 2.1
Name: TextPreprocessing
Version: 3.4.0
Summary: NLP Text perprocessor
Home-page: UNKNOWN
Author: Arun Kesavan
Author-email: <arunkottilukkal@gmail.com>
License: UNKNOWN
Keywords: python,text preprocessing,nlp
Platform: UNKNOWN
Requires-Dist: textblob
Requires-Dist: spacy
Requires-Dist: bs4
